credal/__init__.py
credal/client.py
credal/common/__init__.py
credal/common/types/__init__.py
credal/common/types/collaborator.py
credal/common/types/custom_metadata_value.py
credal/common/types/external_resource_id.py
credal/common/types/operator.py
credal/common/types/resource_identifier.py
credal/common/types/resource_type.py
credal/common/types/role.py
credal/common/types/url.py
credal/copilots/__init__.py
credal/copilots/client.py
credal/copilots/raw_client.py
credal/copilots/types/__init__.py
credal/copilots/types/ai_endpoint_configuration.py
credal/copilots/types/blocked_chunk.py
credal/copilots/types/boolean_field_schema.py
credal/copilots/types/collection_filtered_data.py
credal/copilots/types/configuration.py
credal/copilots/types/create_conversation_response.py
credal/copilots/types/create_copilot_response.py
credal/copilots/types/data_chunk.py
credal/copilots/types/data_filter.py
credal/copilots/types/datetime_field_schema.py
credal/copilots/types/delete_copilot_response.py
credal/copilots/types/end_of_message_chunk.py
credal/copilots/types/error_chunk.py
credal/copilots/types/error_chunk_data.py
credal/copilots/types/export_copilots_response.py
credal/copilots/types/exported_copilot.py
credal/copilots/types/feedback_enum.py
credal/copilots/types/filter.py
credal/copilots/types/final_chunk.py
credal/copilots/types/initial_chunk.py
credal/copilots/types/input_variable.py
credal/copilots/types/inserted_audit_log.py
credal/copilots/types/message_blocked.py
credal/copilots/types/message_feedback.py
credal/copilots/types/message_reply.py
credal/copilots/types/number_field_schema.py
credal/copilots/types/referenced_source.py
credal/copilots/types/response_chunk.py
credal/copilots/types/send_agent_message_response.py
credal/copilots/types/send_message_response.py
credal/copilots/types/streaming_chunk.py
credal/copilots/types/string_field_schema.py
credal/copilots/types/web_search_result.py
credal/core/__init__.py
credal/core/api_error.py
credal-0.1.17.dist-info/METADATA
credal-0.1.17.dist-info/WHEEL
credal-0.1.17.dist-info/RECORD
